crop_row_detector/__init__.py
crop_row_detector/__main__.py
crop_row_detector/crop_row_detector.py
crop_row_detector/orthomosaic_tiler.py
crop_row_detector/py.typed
crop_row_detector-0.2.2.dist-info/METADATA
crop_row_detector-0.2.2.dist-info/WHEEL
crop_row_detector-0.2.2.dist-info/entry_points.txt
crop_row_detector-0.2.2.dist-info/RECORD
