Metadata-Version: 2.4
Name: crop-row-detector
Version: 0.2.2
Summary: Crop Row Detector.
Project-URL: Homepage, https://github.com/henrikmidtiby/TODO
Project-URL: Issues, https://github.com/henrikmidtiby/TODO/issues
Author-email: Henrik Skov Midtiby <hemi@mmmi.sdu.dk>
Maintainer-email: Henrik Skov Midtiby <hemi@mmmi.sdu.dk>, Henrik Dyrberg Egemose <hde@mmmi.sdu.dk>
Classifier: Operating System :: OS Independent
Classifier: Programming Language :: Python :: 3.11
Classifier: Programming Language :: Python :: 3.12
Classifier: Programming Language :: Python :: 3.13
Classifier: Topic :: Scientific/Engineering :: GIS
Classifier: Topic :: Scientific/Engineering :: Image Processing
Requires-Python: >=3.10
Requires-Dist: icecream
Requires-Dist: matplotlib
Requires-Dist: numpy
Requires-Dist: opencv-python
Requires-Dist: pandas
Requires-Dist: pybaselines
Requires-Dist: rasterio
Requires-Dist: scikit-image
Requires-Dist: scipy
Requires-Dist: tqdm
Provides-Extra: dev
Requires-Dist: furo>=2024.8.6; extra == 'dev'
Requires-Dist: mypy>=1.13.0; extra == 'dev'
Requires-Dist: myst-parser>=4.0.0; extra == 'dev'
Requires-Dist: pre-commit>=4.0.1; extra == 'dev'
Requires-Dist: pytest-cov>=6.0.0; extra == 'dev'
Requires-Dist: pytest>=8.3.4; extra == 'dev'
Requires-Dist: sphinx-argparse>=0.5.2; extra == 'dev'
Requires-Dist: sphinx-copybutton>=0.5.2; extra == 'dev'
Requires-Dist: sphinx-reredirects>=0.1.5; extra == 'dev'
Requires-Dist: sphinx>=8.1.3; extra == 'dev'
Provides-Extra: docs
Requires-Dist: furo>=2024.8.6; extra == 'docs'
Requires-Dist: myst-parser>=4.0.0; extra == 'docs'
Requires-Dist: sphinx-argparse>=0.5.2; extra == 'docs'
Requires-Dist: sphinx-copybutton>=0.5.2; extra == 'docs'
Requires-Dist: sphinx-reredirects>=0.1.5; extra == 'docs'
Requires-Dist: sphinx>=8.1.3; extra == 'docs'
Provides-Extra: test
Requires-Dist: pytest-cov>=6.0.0; extra == 'test'
Requires-Dist: pytest>=8.3.4; extra == 'test'
